{
  "generatedAt": "2026-07-01T17:56:01.816880+00:00",
  "source": {
    "name": "Simulation Accuracy Audit",
    "modelVersion": "poisson-v3-dc-startprob"
  },
  "note": "Read-only audit derived from local seed/team data and the current Poisson prediction model. Does not change any simulation behavior or seed data.",
  "baseSeed": 42,
  "ratings": {
    "attack": {
      "highest": [
        {
          "team_id": "ARG",
          "attack": 82.0
        },
        {
          "team_id": "FRA",
          "attack": 81.8
        },
        {
          "team_id": "ENG",
          "attack": 81.7
        },
        {
          "team_id": "BRA",
          "attack": 80.7
        },
        {
          "team_id": "POR",
          "attack": 80.0
        }
      ],
      "lowest": [
        {
          "team_id": "IRQ",
          "attack": 63.1
        },
        {
          "team_id": "CUW",
          "attack": 63.2
        },
        {
          "team_id": "PAN",
          "attack": 63.5
        },
        {
          "team_id": "CPV",
          "attack": 63.6
        },
        {
          "team_id": "JOR",
          "attack": 63.8
        }
      ]
    },
    "defense": {
      "highest": [
        {
          "team_id": "BRA",
          "defense": 81.0
        },
        {
          "team_id": "NED",
          "defense": 80.0
        },
        {
          "team_id": "FRA",
          "defense": 79.6
        },
        {
          "team_id": "ESP",
          "defense": 78.7
        },
        {
          "team_id": "ENG",
          "defense": 78.6
        }
      ],
      "lowest": [
        {
          "team_id": "IRQ",
          "defense": 66.4
        },
        {
          "team_id": "JOR",
          "defense": 67.0
        },
        {
          "team_id": "CPV",
          "defense": 67.1
        },
        {
          "team_id": "UZB",
          "defense": 67.3
        },
        {
          "team_id": "QAT",
          "defense": 68.0
        }
      ]
    },
    "strength": {
      "highest": [
        {
          "team_id": "ARG",
          "strength": 92.2
        },
        {
          "team_id": "ESP",
          "strength": 90.2
        },
        {
          "team_id": "FRA",
          "strength": 88.2
        },
        {
          "team_id": "ENG",
          "strength": 86.2
        },
        {
          "team_id": "POR",
          "strength": 84.9
        }
      ],
      "lowest": [
        {
          "team_id": "CUW",
          "strength": 42.7
        },
        {
          "team_id": "NZL",
          "strength": 43.6
        },
        {
          "team_id": "HAI",
          "strength": 43.6
        },
        {
          "team_id": "CPV",
          "strength": 43.7
        },
        {
          "team_id": "GHA",
          "strength": 45.4
        }
      ]
    }
  },
  "topTwentyMatchupSample": [
    {
      "home_team_id": "ARG",
      "away_team_id": "ESP",
      "home_fifa_rank": 1,
      "away_fifa_rank": 2,
      "rank_gap": 1,
      "home_win_pct": 42.9,
      "draw_pct": 27.4,
      "away_win_pct": 29.7,
      "home_expected_goals": 1.54,
      "away_expected_goals": 1.25
    },
    {
      "home_team_id": "ARG",
      "away_team_id": "FRA",
      "home_fifa_rank": 1,
      "away_fifa_rank": 3,
      "rank_gap": 2,
      "home_win_pct": 42.9,
      "draw_pct": 27.4,
      "away_win_pct": 29.7,
      "home_expected_goals": 1.54,
      "away_expected_goals": 1.25
    },
    {
      "home_team_id": "ARG",
      "away_team_id": "ENG",
      "home_fifa_rank": 1,
      "away_fifa_rank": 4,
      "rank_gap": 3,
      "home_win_pct": 43.1,
      "draw_pct": 27.4,
      "away_win_pct": 29.5,
      "home_expected_goals": 1.54,
      "away_expected_goals": 1.24
    },
    {
      "home_team_id": "ARG",
      "away_team_id": "POR",
      "home_fifa_rank": 1,
      "away_fifa_rank": 5,
      "rank_gap": 4,
      "home_win_pct": 46.5,
      "draw_pct": 26.9,
      "away_win_pct": 26.6,
      "home_expected_goals": 1.62,
      "away_expected_goals": 1.18
    },
    {
      "home_team_id": "ARG",
      "away_team_id": "BRA",
      "home_fifa_rank": 1,
      "away_fifa_rank": 6,
      "rank_gap": 5,
      "home_win_pct": 50.2,
      "draw_pct": 26.1,
      "away_win_pct": 23.7,
      "home_expected_goals": 1.71,
      "away_expected_goals": 1.12
    },
    {
      "home_team_id": "ARG",
      "away_team_id": "NED",
      "home_fifa_rank": 1,
      "away_fifa_rank": 7,
      "rank_gap": 6,
      "home_win_pct": 52.7,
      "draw_pct": 25.5,
      "away_win_pct": 21.8,
      "home_expected_goals": 1.78,
      "away_expected_goals": 1.08
    },
    {
      "home_team_id": "ARG",
      "away_team_id": "MAR",
      "home_fifa_rank": 1,
      "away_fifa_rank": 8,
      "rank_gap": 7,
      "home_win_pct": 51.3,
      "draw_pct": 25.9,
      "away_win_pct": 22.8,
      "home_expected_goals": 1.74,
      "away_expected_goals": 1.1
    },
    {
      "home_team_id": "ARG",
      "away_team_id": "BEL",
      "home_fifa_rank": 1,
      "away_fifa_rank": 9,
      "rank_gap": 8,
      "home_win_pct": 51.9,
      "draw_pct": 25.7,
      "away_win_pct": 22.4,
      "home_expected_goals": 1.76,
      "away_expected_goals": 1.09
    },
    {
      "home_team_id": "ARG",
      "away_team_id": "GER",
      "home_fifa_rank": 1,
      "away_fifa_rank": 10,
      "rank_gap": 9,
      "home_win_pct": 50.7,
      "draw_pct": 26.0,
      "away_win_pct": 23.3,
      "home_expected_goals": 1.73,
      "away_expected_goals": 1.11
    },
    {
      "home_team_id": "ARG",
      "away_team_id": "CRO",
      "home_fifa_rank": 1,
      "away_fifa_rank": 10,
      "rank_gap": 9,
      "home_win_pct": 51.2,
      "draw_pct": 25.9,
      "away_win_pct": 22.9,
      "home_expected_goals": 1.74,
      "away_expected_goals": 1.1
    },
    {
      "home_team_id": "ARG",
      "away_team_id": "MEX",
      "home_fifa_rank": 1,
      "away_fifa_rank": 14,
      "rank_gap": 13,
      "home_win_pct": 59.1,
      "draw_pct": 23.6,
      "away_win_pct": 17.3,
      "home_expected_goals": 1.96,
      "away_expected_goals": 0.98
    },
    {
      "home_team_id": "ARG",
      "away_team_id": "COL",
      "home_fifa_rank": 1,
      "away_fifa_rank": 14,
      "rank_gap": 13,
      "home_win_pct": 56.1,
      "draw_pct": 24.5,
      "away_win_pct": 19.3,
      "home_expected_goals": 1.87,
      "away_expected_goals": 1.02
    },
    {
      "home_team_id": "ARG",
      "away_team_id": "URU",
      "home_fifa_rank": 1,
      "away_fifa_rank": 16,
      "rank_gap": 15,
      "home_win_pct": 60.8,
      "draw_pct": 23.0,
      "away_win_pct": 16.2,
      "home_expected_goals": 2.01,
      "away_expected_goals": 0.95
    },
    {
      "home_team_id": "ARG",
      "away_team_id": "USA",
      "home_fifa_rank": 1,
      "away_fifa_rank": 17,
      "rank_gap": 16,
      "home_win_pct": 56.6,
      "draw_pct": 24.4,
      "away_win_pct": 19.0,
      "home_expected_goals": 1.89,
      "away_expected_goals": 1.02
    },
    {
      "home_team_id": "ARG",
      "away_team_id": "JPN",
      "home_fifa_rank": 1,
      "away_fifa_rank": 18,
      "rank_gap": 17,
      "home_win_pct": 56.4,
      "draw_pct": 24.5,
      "away_win_pct": 19.2,
      "home_expected_goals": 1.88,
      "away_expected_goals": 1.02
    },
    {
      "home_team_id": "ARG",
      "away_team_id": "SEN",
      "home_fifa_rank": 1,
      "away_fifa_rank": 18,
      "rank_gap": 17,
      "home_win_pct": 60.3,
      "draw_pct": 23.1,
      "away_win_pct": 16.6,
      "home_expected_goals": 1.99,
      "away_expected_goals": 0.96
    },
    {
      "home_team_id": "ARG",
      "away_team_id": "SUI",
      "home_fifa_rank": 1,
      "away_fifa_rank": 19,
      "rank_gap": 18,
      "home_win_pct": 66.2,
      "draw_pct": 20.8,
      "away_win_pct": 13.0,
      "home_expected_goals": 2.18,
      "away_expected_goals": 0.88
    },
    {
      "home_team_id": "ARG",
      "away_team_id": "IRN",
      "home_fifa_rank": 1,
      "away_fifa_rank": 20,
      "rank_gap": 19,
      "home_win_pct": 70.6,
      "draw_pct": 18.9,
      "away_win_pct": 10.6,
      "home_expected_goals": 2.34,
      "away_expected_goals": 0.82
    },
    {
      "home_team_id": "ARG",
      "away_team_id": "TUR",
      "home_fifa_rank": 1,
      "away_fifa_rank": 22,
      "rank_gap": 21,
      "home_win_pct": 58.5,
      "draw_pct": 23.8,
      "away_win_pct": 17.7,
      "home_expected_goals": 1.94,
      "away_expected_goals": 0.99
    },
    {
      "home_team_id": "ESP",
      "away_team_id": "FRA",
      "home_fifa_rank": 2,
      "away_fifa_rank": 3,
      "rank_gap": 1,
      "home_win_pct": 37.6,
      "draw_pct": 27.8,
      "away_win_pct": 34.5,
      "home_expected_goals": 1.42,
      "away_expected_goals": 1.35
    },
    {
      "home_team_id": "ESP",
      "away_team_id": "ENG",
      "home_fifa_rank": 2,
      "away_fifa_rank": 4,
      "rank_gap": 2,
      "home_win_pct": 37.8,
      "draw_pct": 27.8,
      "away_win_pct": 34.3,
      "home_expected_goals": 1.42,
      "away_expected_goals": 1.35
    },
    {
      "home_team_id": "ESP",
      "away_team_id": "POR",
      "home_fifa_rank": 2,
      "away_fifa_rank": 5,
      "rank_gap": 3,
      "home_win_pct": 41.1,
      "draw_pct": 27.6,
      "away_win_pct": 31.3,
      "home_expected_goals": 1.5,
      "away_expected_goals": 1.28
    },
    {
      "home_team_id": "ESP",
      "away_team_id": "BRA",
      "home_fifa_rank": 2,
      "away_fifa_rank": 6,
      "rank_gap": 4,
      "home_win_pct": 44.8,
      "draw_pct": 27.2,
      "away_win_pct": 28.1,
      "home_expected_goals": 1.58,
      "away_expected_goals": 1.21
    },
    {
      "home_team_id": "ESP",
      "away_team_id": "NED",
      "home_fifa_rank": 2,
      "away_fifa_rank": 7,
      "rank_gap": 5,
      "home_win_pct": 47.2,
      "draw_pct": 26.8,
      "away_win_pct": 26.0,
      "home_expected_goals": 1.64,
      "away_expected_goals": 1.17
    },
    {
      "home_team_id": "ESP",
      "away_team_id": "MAR",
      "home_fifa_rank": 2,
      "away_fifa_rank": 8,
      "rank_gap": 6,
      "home_win_pct": 45.8,
      "draw_pct": 27.0,
      "away_win_pct": 27.2,
      "home_expected_goals": 1.61,
      "away_expected_goals": 1.19
    },
    {
      "home_team_id": "ESP",
      "away_team_id": "BEL",
      "home_fifa_rank": 2,
      "away_fifa_rank": 9,
      "rank_gap": 7,
      "home_win_pct": 46.5,
      "draw_pct": 26.9,
      "away_win_pct": 26.6,
      "home_expected_goals": 1.62,
      "away_expected_goals": 1.18
    },
    {
      "home_team_id": "ESP",
      "away_team_id": "GER",
      "home_fifa_rank": 2,
      "away_fifa_rank": 10,
      "rank_gap": 8,
      "home_win_pct": 45.3,
      "draw_pct": 27.1,
      "away_win_pct": 27.6,
      "home_expected_goals": 1.59,
      "away_expected_goals": 1.2
    },
    {
      "home_team_id": "ESP",
      "away_team_id": "CRO",
      "home_fifa_rank": 2,
      "away_fifa_rank": 10,
      "rank_gap": 8,
      "home_win_pct": 45.7,
      "draw_pct": 27.0,
      "away_win_pct": 27.2,
      "home_expected_goals": 1.6,
      "away_expected_goals": 1.19
    },
    {
      "home_team_id": "ESP",
      "away_team_id": "MEX",
      "home_fifa_rank": 2,
      "away_fifa_rank": 14,
      "rank_gap": 12,
      "home_win_pct": 53.7,
      "draw_pct": 25.3,
      "away_win_pct": 21.1,
      "home_expected_goals": 1.8,
      "away_expected_goals": 1.06
    },
    {
      "home_team_id": "ESP",
      "away_team_id": "COL",
      "home_fifa_rank": 2,
      "away_fifa_rank": 14,
      "rank_gap": 12,
      "home_win_pct": 50.7,
      "draw_pct": 26.0,
      "away_win_pct": 23.3,
      "home_expected_goals": 1.73,
      "away_expected_goals": 1.11
    },
    {
      "home_team_id": "ESP",
      "away_team_id": "URU",
      "home_fifa_rank": 2,
      "away_fifa_rank": 16,
      "rank_gap": 14,
      "home_win_pct": 55.4,
      "draw_pct": 24.8,
      "away_win_pct": 19.8,
      "home_expected_goals": 1.85,
      "away_expected_goals": 1.03
    },
    {
      "home_team_id": "ESP",
      "away_team_id": "USA",
      "home_fifa_rank": 2,
      "away_fifa_rank": 17,
      "rank_gap": 15,
      "home_win_pct": 51.2,
      "draw_pct": 25.9,
      "away_win_pct": 22.9,
      "home_expected_goals": 1.74,
      "away_expected_goals": 1.1
    },
    {
      "home_team_id": "ESP",
      "away_team_id": "JPN",
      "home_fifa_rank": 2,
      "away_fifa_rank": 18,
      "rank_gap": 16,
      "home_win_pct": 50.9,
      "draw_pct": 26.0,
      "away_win_pct": 23.1,
      "home_expected_goals": 1.73,
      "away_expected_goals": 1.11
    },
    {
      "home_team_id": "ESP",
      "away_team_id": "SEN",
      "home_fifa_rank": 2,
      "away_fifa_rank": 18,
      "rank_gap": 16,
      "home_win_pct": 54.9,
      "draw_pct": 24.9,
      "away_win_pct": 20.2,
      "home_expected_goals": 1.84,
      "away_expected_goals": 1.04
    },
    {
      "home_team_id": "ESP",
      "away_team_id": "SUI",
      "home_fifa_rank": 2,
      "away_fifa_rank": 19,
      "rank_gap": 17,
      "home_win_pct": 61.0,
      "draw_pct": 22.9,
      "away_win_pct": 16.1,
      "home_expected_goals": 2.01,
      "away_expected_goals": 0.95
    },
    {
      "home_team_id": "ESP",
      "away_team_id": "IRN",
      "home_fifa_rank": 2,
      "away_fifa_rank": 20,
      "rank_gap": 18,
      "home_win_pct": 65.6,
      "draw_pct": 21.1,
      "away_win_pct": 13.3,
      "home_expected_goals": 2.16,
      "away_expected_goals": 0.89
    },
    {
      "home_team_id": "ESP",
      "away_team_id": "TUR",
      "home_fifa_rank": 2,
      "away_fifa_rank": 22,
      "rank_gap": 20,
      "home_win_pct": 53.1,
      "draw_pct": 25.4,
      "away_win_pct": 21.5,
      "home_expected_goals": 1.79,
      "away_expected_goals": 1.07
    },
    {
      "home_team_id": "FRA",
      "away_team_id": "ENG",
      "home_fifa_rank": 3,
      "away_fifa_rank": 4,
      "rank_gap": 1,
      "home_win_pct": 37.9,
      "draw_pct": 27.8,
      "away_win_pct": 34.3,
      "home_expected_goals": 1.42,
      "away_expected_goals": 1.35
    },
    {
      "home_team_id": "FRA",
      "away_team_id": "POR",
      "home_fifa_rank": 3,
      "away_fifa_rank": 5,
      "rank_gap": 2,
      "home_win_pct": 41.2,
      "draw_pct": 27.6,
      "away_win_pct": 31.2,
      "home_expected_goals": 1.5,
      "away_expected_goals": 1.28
    },
    {
      "home_team_id": "FRA",
      "away_team_id": "BRA",
      "home_fifa_rank": 3,
      "away_fifa_rank": 6,
      "rank_gap": 3,
      "home_win_pct": 44.8,
      "draw_pct": 27.2,
      "away_win_pct": 28.0,
      "home_expected_goals": 1.58,
      "away_expected_goals": 1.21
    },
    {
      "home_team_id": "FRA",
      "away_team_id": "NED",
      "home_fifa_rank": 3,
      "away_fifa_rank": 7,
      "rank_gap": 4,
      "home_win_pct": 47.3,
      "draw_pct": 26.7,
      "away_win_pct": 26.0,
      "home_expected_goals": 1.64,
      "away_expected_goals": 1.17
    },
    {
      "home_team_id": "FRA",
      "away_team_id": "MAR",
      "home_fifa_rank": 3,
      "away_fifa_rank": 8,
      "rank_gap": 5,
      "home_win_pct": 45.9,
      "draw_pct": 27.0,
      "away_win_pct": 27.1,
      "home_expected_goals": 1.61,
      "away_expected_goals": 1.19
    },
    {
      "home_team_id": "FRA",
      "away_team_id": "BEL",
      "home_fifa_rank": 3,
      "away_fifa_rank": 9,
      "rank_gap": 6,
      "home_win_pct": 46.5,
      "draw_pct": 26.9,
      "away_win_pct": 26.6,
      "home_expected_goals": 1.62,
      "away_expected_goals": 1.18
    },
    {
      "home_team_id": "FRA",
      "away_team_id": "GER",
      "home_fifa_rank": 3,
      "away_fifa_rank": 10,
      "rank_gap": 7,
      "home_win_pct": 45.3,
      "draw_pct": 27.1,
      "away_win_pct": 27.6,
      "home_expected_goals": 1.59,
      "away_expected_goals": 1.2
    },
    {
      "home_team_id": "FRA",
      "away_team_id": "CRO",
      "home_fifa_rank": 3,
      "away_fifa_rank": 10,
      "rank_gap": 7,
      "home_win_pct": 45.8,
      "draw_pct": 27.0,
      "away_win_pct": 27.2,
      "home_expected_goals": 1.61,
      "away_expected_goals": 1.19
    },
    {
      "home_team_id": "FRA",
      "away_team_id": "MEX",
      "home_fifa_rank": 3,
      "away_fifa_rank": 14,
      "rank_gap": 11,
      "home_win_pct": 53.7,
      "draw_pct": 25.2,
      "away_win_pct": 21.0,
      "home_expected_goals": 1.81,
      "away_expected_goals": 1.06
    },
    {
      "home_team_id": "FRA",
      "away_team_id": "COL",
      "home_fifa_rank": 3,
      "away_fifa_rank": 14,
      "rank_gap": 11,
      "home_win_pct": 50.7,
      "draw_pct": 26.0,
      "away_win_pct": 23.2,
      "home_expected_goals": 1.73,
      "away_expected_goals": 1.11
    },
    {
      "home_team_id": "FRA",
      "away_team_id": "URU",
      "home_fifa_rank": 3,
      "away_fifa_rank": 16,
      "rank_gap": 13,
      "home_win_pct": 55.5,
      "draw_pct": 24.7,
      "away_win_pct": 19.8,
      "home_expected_goals": 1.85,
      "away_expected_goals": 1.03
    },
    {
      "home_team_id": "FRA",
      "away_team_id": "USA",
      "home_fifa_rank": 3,
      "away_fifa_rank": 17,
      "rank_gap": 14,
      "home_win_pct": 51.2,
      "draw_pct": 25.9,
      "away_win_pct": 22.9,
      "home_expected_goals": 1.74,
      "away_expected_goals": 1.1
    },
    {
      "home_team_id": "FRA",
      "away_team_id": "JPN",
      "home_fifa_rank": 3,
      "away_fifa_rank": 18,
      "rank_gap": 15,
      "home_win_pct": 51.0,
      "draw_pct": 26.0,
      "away_win_pct": 23.1,
      "home_expected_goals": 1.73,
      "away_expected_goals": 1.11
    },
    {
      "home_team_id": "FRA",
      "away_team_id": "SEN",
      "home_fifa_rank": 3,
      "away_fifa_rank": 18,
      "rank_gap": 15,
      "home_win_pct": 54.9,
      "draw_pct": 24.9,
      "away_win_pct": 20.2,
      "home_expected_goals": 1.84,
      "away_expected_goals": 1.04
    },
    {
      "home_team_id": "FRA",
      "away_team_id": "SUI",
      "home_fifa_rank": 3,
      "away_fifa_rank": 19,
      "rank_gap": 16,
      "home_win_pct": 61.1,
      "draw_pct": 22.9,
      "away_win_pct": 16.1,
      "home_expected_goals": 2.01,
      "away_expected_goals": 0.95
    },
    {
      "home_team_id": "FRA",
      "away_team_id": "IRN",
      "home_fifa_rank": 3,
      "away_fifa_rank": 20,
      "rank_gap": 17,
      "home_win_pct": 65.6,
      "draw_pct": 21.1,
      "away_win_pct": 13.3,
      "home_expected_goals": 2.16,
      "away_expected_goals": 0.89
    },
    {
      "home_team_id": "FRA",
      "away_team_id": "TUR",
      "home_fifa_rank": 3,
      "away_fifa_rank": 22,
      "rank_gap": 19,
      "home_win_pct": 53.2,
      "draw_pct": 25.4,
      "away_win_pct": 21.4,
      "home_expected_goals": 1.79,
      "away_expected_goals": 1.07
    },
    {
      "home_team_id": "ENG",
      "away_team_id": "POR",
      "home_fifa_rank": 4,
      "away_fifa_rank": 5,
      "rank_gap": 1,
      "home_win_pct": 40.9,
      "draw_pct": 27.6,
      "away_win_pct": 31.4,
      "home_expected_goals": 1.49,
      "away_expected_goals": 1.28
    },
    {
      "home_team_id": "ENG",
      "away_team_id": "BRA",
      "home_fifa_rank": 4,
      "away_fifa_rank": 6,
      "rank_gap": 2,
      "home_win_pct": 44.6,
      "draw_pct": 27.2,
      "away_win_pct": 28.2,
      "home_expected_goals": 1.58,
      "away_expected_goals": 1.21
    },
    {
      "home_team_id": "ENG",
      "away_team_id": "NED",
      "home_fifa_rank": 4,
      "away_fifa_rank": 7,
      "rank_gap": 3,
      "home_win_pct": 47.0,
      "draw_pct": 26.8,
      "away_win_pct": 26.2,
      "home_expected_goals": 1.64,
      "away_expected_goals": 1.17
    },
    {
      "home_team_id": "ENG",
      "away_team_id": "MAR",
      "home_fifa_rank": 4,
      "away_fifa_rank": 8,
      "rank_gap": 4,
      "home_win_pct": 45.7,
      "draw_pct": 27.0,
      "away_win_pct": 27.3,
      "home_expected_goals": 1.6,
      "away_expected_goals": 1.2
    },
    {
      "home_team_id": "ENG",
      "away_team_id": "BEL",
      "home_fifa_rank": 4,
      "away_fifa_rank": 9,
      "rank_gap": 5,
      "home_win_pct": 46.3,
      "draw_pct": 26.9,
      "away_win_pct": 26.8,
      "home_expected_goals": 1.62,
      "away_expected_goals": 1.18
    },
    {
      "home_team_id": "ENG",
      "away_team_id": "GER",
      "home_fifa_rank": 4,
      "away_fifa_rank": 10,
      "rank_gap": 6,
      "home_win_pct": 45.1,
      "draw_pct": 27.1,
      "away_win_pct": 27.8,
      "home_expected_goals": 1.59,
      "away_expected_goals": 1.21
    },
    {
      "home_team_id": "ENG",
      "away_team_id": "CRO",
      "home_fifa_rank": 4,
      "away_fifa_rank": 10,
      "rank_gap": 6,
      "home_win_pct": 45.6,
      "draw_pct": 27.1,
      "away_win_pct": 27.4,
      "home_expected_goals": 1.6,
      "away_expected_goals": 1.2
    },
    {
      "home_team_id": "ENG",
      "away_team_id": "MEX",
      "home_fifa_rank": 4,
      "away_fifa_rank": 14,
      "rank_gap": 10,
      "home_win_pct": 53.5,
      "draw_pct": 25.3,
      "away_win_pct": 21.2,
      "home_expected_goals": 1.8,
      "away_expected_goals": 1.06
    },
    {
      "home_team_id": "ENG",
      "away_team_id": "COL",
      "home_fifa_rank": 4,
      "away_fifa_rank": 14,
      "rank_gap": 10,
      "home_win_pct": 50.5,
      "draw_pct": 26.1,
      "away_win_pct": 23.4,
      "home_expected_goals": 1.72,
      "away_expected_goals": 1.11
    },
    {
      "home_team_id": "ENG",
      "away_team_id": "URU",
      "home_fifa_rank": 4,
      "away_fifa_rank": 16,
      "rank_gap": 12,
      "home_win_pct": 55.2,
      "draw_pct": 24.8,
      "away_win_pct": 20.0,
      "home_expected_goals": 1.85,
      "away_expected_goals": 1.04
    },
    {
      "home_team_id": "ENG",
      "away_team_id": "USA",
      "home_fifa_rank": 4,
      "away_fifa_rank": 17,
      "rank_gap": 13,
      "home_win_pct": 51.0,
      "draw_pct": 25.9,
      "away_win_pct": 23.0,
      "home_expected_goals": 1.73,
      "away_expected_goals": 1.1
    },
    {
      "home_team_id": "ENG",
      "away_team_id": "JPN",
      "home_fifa_rank": 4,
      "away_fifa_rank": 18,
      "rank_gap": 14,
      "home_win_pct": 50.7,
      "draw_pct": 26.0,
      "away_win_pct": 23.3,
      "home_expected_goals": 1.73,
      "away_expected_goals": 1.11
    },
    {
      "home_team_id": "ENG",
      "away_team_id": "SEN",
      "home_fifa_rank": 4,
      "away_fifa_rank": 18,
      "rank_gap": 14,
      "home_win_pct": 54.7,
      "draw_pct": 25.0,
      "away_win_pct": 20.3,
      "home_expected_goals": 1.83,
      "away_expected_goals": 1.05
    },
    {
      "home_team_id": "ENG",
      "away_team_id": "SUI",
      "home_fifa_rank": 4,
      "away_fifa_rank": 19,
      "rank_gap": 15,
      "home_win_pct": 60.8,
      "draw_pct": 22.9,
      "away_win_pct": 16.2,
      "home_expected_goals": 2.01,
      "away_expected_goals": 0.95
    },
    {
      "home_team_id": "ENG",
      "away_team_id": "IRN",
      "home_fifa_rank": 4,
      "away_fifa_rank": 20,
      "rank_gap": 16,
      "home_win_pct": 65.4,
      "draw_pct": 21.2,
      "away_win_pct": 13.5,
      "home_expected_goals": 2.15,
      "away_expected_goals": 0.89
    },
    {
      "home_team_id": "ENG",
      "away_team_id": "TUR",
      "home_fifa_rank": 4,
      "away_fifa_rank": 22,
      "rank_gap": 18,
      "home_win_pct": 52.9,
      "draw_pct": 25.5,
      "away_win_pct": 21.6,
      "home_expected_goals": 1.78,
      "away_expected_goals": 1.07
    },
    {
      "home_team_id": "POR",
      "away_team_id": "BRA",
      "home_fifa_rank": 5,
      "away_fifa_rank": 6,
      "rank_gap": 1,
      "home_win_pct": 41.2,
      "draw_pct": 27.6,
      "away_win_pct": 31.2,
      "home_expected_goals": 1.5,
      "away_expected_goals": 1.28
    },
    {
      "home_team_id": "POR",
      "away_team_id": "NED",
      "home_fifa_rank": 5,
      "away_fifa_rank": 7,
      "rank_gap": 2,
      "home_win_pct": 43.7,
      "draw_pct": 27.3,
      "away_win_pct": 29.0,
      "home_expected_goals": 1.56,
      "away_expected_goals": 1.23
    },
    {
      "home_team_id": "POR",
      "away_team_id": "MAR",
      "home_fifa_rank": 5,
      "away_fifa_rank": 8,
      "rank_gap": 3,
      "home_win_pct": 42.3,
      "draw_pct": 27.5,
      "away_win_pct": 30.2,
      "home_expected_goals": 1.52,
      "away_expected_goals": 1.26
    },
    {
      "home_team_id": "POR",
      "away_team_id": "BEL",
      "home_fifa_rank": 5,
      "away_fifa_rank": 9,
      "rank_gap": 4,
      "home_win_pct": 42.9,
      "draw_pct": 27.4,
      "away_win_pct": 29.7,
      "home_expected_goals": 1.54,
      "away_expected_goals": 1.25
    },
    {
      "home_team_id": "POR",
      "away_team_id": "GER",
      "home_fifa_rank": 5,
      "away_fifa_rank": 10,
      "rank_gap": 5,
      "home_win_pct": 41.7,
      "draw_pct": 27.6,
      "away_win_pct": 30.7,
      "home_expected_goals": 1.51,
      "away_expected_goals": 1.27
    },
    {
      "home_team_id": "POR",
      "away_team_id": "CRO",
      "home_fifa_rank": 5,
      "away_fifa_rank": 10,
      "rank_gap": 5,
      "home_win_pct": 42.2,
      "draw_pct": 27.5,
      "away_win_pct": 30.3,
      "home_expected_goals": 1.52,
      "away_expected_goals": 1.26
    },
    {
      "home_team_id": "POR",
      "away_team_id": "MEX",
      "home_fifa_rank": 5,
      "away_fifa_rank": 14,
      "rank_gap": 9,
      "home_win_pct": 50.1,
      "draw_pct": 26.2,
      "away_win_pct": 23.8,
      "home_expected_goals": 1.71,
      "away_expected_goals": 1.12
    },
    {
      "home_team_id": "POR",
      "away_team_id": "COL",
      "home_fifa_rank": 5,
      "away_fifa_rank": 14,
      "rank_gap": 9,
      "home_win_pct": 47.1,
      "draw_pct": 26.8,
      "away_win_pct": 26.1,
      "home_expected_goals": 1.64,
      "away_expected_goals": 1.17
    },
    {
      "home_team_id": "POR",
      "away_team_id": "URU",
      "home_fifa_rank": 5,
      "away_fifa_rank": 16,
      "rank_gap": 11,
      "home_win_pct": 51.8,
      "draw_pct": 25.8,
      "away_win_pct": 22.4,
      "home_expected_goals": 1.76,
      "away_expected_goals": 1.09
    },
    {
      "home_team_id": "POR",
      "away_team_id": "USA",
      "home_fifa_rank": 5,
      "away_fifa_rank": 17,
      "rank_gap": 12,
      "home_win_pct": 47.6,
      "draw_pct": 26.7,
      "away_win_pct": 25.7,
      "home_expected_goals": 1.65,
      "away_expected_goals": 1.16
    },
    {
      "home_team_id": "POR",
      "away_team_id": "JPN",
      "home_fifa_rank": 5,
      "away_fifa_rank": 18,
      "rank_gap": 13,
      "home_win_pct": 47.3,
      "draw_pct": 26.7,
      "away_win_pct": 25.9,
      "home_expected_goals": 1.64,
      "away_expected_goals": 1.17
    },
    {
      "home_team_id": "POR",
      "away_team_id": "SEN",
      "home_fifa_rank": 5,
      "away_fifa_rank": 18,
      "rank_gap": 13,
      "home_win_pct": 51.3,
      "draw_pct": 25.9,
      "away_win_pct": 22.8,
      "home_expected_goals": 1.74,
      "away_expected_goals": 1.1
    },
    {
      "home_team_id": "POR",
      "away_team_id": "SUI",
      "home_fifa_rank": 5,
      "away_fifa_rank": 19,
      "rank_gap": 14,
      "home_win_pct": 57.5,
      "draw_pct": 24.1,
      "away_win_pct": 18.4,
      "home_expected_goals": 1.91,
      "away_expected_goals": 1.0
    },
    {
      "home_team_id": "POR",
      "away_team_id": "IRN",
      "home_fifa_rank": 5,
      "away_fifa_rank": 20,
      "rank_gap": 15,
      "home_win_pct": 62.1,
      "draw_pct": 22.5,
      "away_win_pct": 15.4,
      "home_expected_goals": 2.05,
      "away_expected_goals": 0.94
    },
    {
      "home_team_id": "POR",
      "away_team_id": "TUR",
      "home_fifa_rank": 5,
      "away_fifa_rank": 22,
      "rank_gap": 17,
      "home_win_pct": 49.5,
      "draw_pct": 26.3,
      "away_win_pct": 24.2,
      "home_expected_goals": 1.7,
      "away_expected_goals": 1.13
    },
    {
      "home_team_id": "BRA",
      "away_team_id": "NED",
      "home_fifa_rank": 6,
      "away_fifa_rank": 7,
      "rank_gap": 1,
      "home_win_pct": 40.0,
      "draw_pct": 27.7,
      "away_win_pct": 32.3,
      "home_expected_goals": 1.47,
      "away_expected_goals": 1.3
    },
    {
      "home_team_id": "BRA",
      "away_team_id": "MAR",
      "home_fifa_rank": 6,
      "away_fifa_rank": 8,
      "rank_gap": 2,
      "home_win_pct": 38.7,
      "draw_pct": 27.8,
      "away_win_pct": 33.5,
      "home_expected_goals": 1.44,
      "away_expected_goals": 1.33
    },
    {
      "home_team_id": "BRA",
      "away_team_id": "BEL",
      "home_fifa_rank": 6,
      "away_fifa_rank": 9,
      "rank_gap": 3,
      "home_win_pct": 39.3,
      "draw_pct": 27.8,
      "away_win_pct": 33.0,
      "home_expected_goals": 1.46,
      "away_expected_goals": 1.32
    },
    {
      "home_team_id": "BRA",
      "away_team_id": "GER",
      "home_fifa_rank": 6,
      "away_fifa_rank": 10,
      "rank_gap": 4,
      "home_win_pct": 38.2,
      "draw_pct": 27.8,
      "away_win_pct": 34.0,
      "home_expected_goals": 1.43,
      "away_expected_goals": 1.34
    },
    {
      "home_team_id": "BRA",
      "away_team_id": "CRO",
      "home_fifa_rank": 6,
      "away_fifa_rank": 10,
      "rank_gap": 4,
      "home_win_pct": 38.6,
      "draw_pct": 27.8,
      "away_win_pct": 33.6,
      "home_expected_goals": 1.44,
      "away_expected_goals": 1.33
    },
    {
      "home_team_id": "BRA",
      "away_team_id": "MEX",
      "home_fifa_rank": 6,
      "away_fifa_rank": 14,
      "rank_gap": 8,
      "home_win_pct": 46.3,
      "draw_pct": 26.9,
      "away_win_pct": 26.7,
      "home_expected_goals": 1.62,
      "away_expected_goals": 1.18
    },
    {
      "home_team_id": "BRA",
      "away_team_id": "COL",
      "home_fifa_rank": 6,
      "away_fifa_rank": 14,
      "rank_gap": 8,
      "home_win_pct": 43.4,
      "draw_pct": 27.4,
      "away_win_pct": 29.2,
      "home_expected_goals": 1.55,
      "away_expected_goals": 1.24
    },
    {
      "home_team_id": "BRA",
      "away_team_id": "URU",
      "home_fifa_rank": 6,
      "away_fifa_rank": 16,
      "rank_gap": 10,
      "home_win_pct": 48.1,
      "draw_pct": 26.6,
      "away_win_pct": 25.3,
      "home_expected_goals": 1.66,
      "away_expected_goals": 1.15
    },
    {
      "home_team_id": "BRA",
      "away_team_id": "USA",
      "home_fifa_rank": 6,
      "away_fifa_rank": 17,
      "rank_gap": 11,
      "home_win_pct": 43.9,
      "draw_pct": 27.3,
      "away_win_pct": 28.8,
      "home_expected_goals": 1.56,
      "away_expected_goals": 1.23
    },
    {
      "home_team_id": "BRA",
      "away_team_id": "JPN",
      "home_fifa_rank": 6,
      "away_fifa_rank": 18,
      "rank_gap": 12,
      "home_win_pct": 43.6,
      "draw_pct": 27.3,
      "away_win_pct": 29.0,
      "home_expected_goals": 1.55,
      "away_expected_goals": 1.23
    },
    {
      "home_team_id": "BRA",
      "away_team_id": "SEN",
      "home_fifa_rank": 6,
      "away_fifa_rank": 18,
      "rank_gap": 12,
      "home_win_pct": 47.6,
      "draw_pct": 26.7,
      "away_win_pct": 25.7,
      "home_expected_goals": 1.65,
      "away_expected_goals": 1.16
    },
    {
      "home_team_id": "BRA",
      "away_team_id": "SUI",
      "home_fifa_rank": 6,
      "away_fifa_rank": 19,
      "rank_gap": 13,
      "home_win_pct": 53.8,
      "draw_pct": 25.2,
      "away_win_pct": 21.0,
      "home_expected_goals": 1.81,
      "away_expected_goals": 1.06
    },
    {
      "home_team_id": "BRA",
      "away_team_id": "IRN",
      "home_fifa_rank": 6,
      "away_fifa_rank": 20,
      "rank_gap": 14,
      "home_win_pct": 58.5,
      "draw_pct": 23.8,
      "away_win_pct": 17.8,
      "home_expected_goals": 1.94,
      "away_expected_goals": 0.99
    },
    {
      "home_team_id": "BRA",
      "away_team_id": "TUR",
      "home_fifa_rank": 6,
      "away_fifa_rank": 22,
      "rank_gap": 16,
      "home_win_pct": 45.8,
      "draw_pct": 27.0,
      "away_win_pct": 27.2,
      "home_expected_goals": 1.61,
      "away_expected_goals": 1.19
    },
    {
      "home_team_id": "NED",
      "away_team_id": "MAR",
      "home_fifa_rank": 7,
      "away_fifa_rank": 8,
      "rank_gap": 1,
      "home_win_pct": 36.3,
      "draw_pct": 27.9,
      "away_win_pct": 35.8,
      "home_expected_goals": 1.39,
      "away_expected_goals": 1.38
    },
    {
      "home_team_id": "NED",
      "away_team_id": "BEL",
      "home_fifa_rank": 7,
      "away_fifa_rank": 9,
      "rank_gap": 2,
      "home_win_pct": 36.9,
      "draw_pct": 27.8,
      "away_win_pct": 35.2,
      "home_expected_goals": 1.4,
      "away_expected_goals": 1.37
    },
    {
      "home_team_id": "NED",
      "away_team_id": "GER",
      "home_fifa_rank": 7,
      "away_fifa_rank": 10,
      "rank_gap": 3,
      "home_win_pct": 35.8,
      "draw_pct": 27.9,
      "away_win_pct": 36.3,
      "home_expected_goals": 1.38,
      "away_expected_goals": 1.39
    },
    {
      "home_team_id": "NED",
      "away_team_id": "CRO",
      "home_fifa_rank": 7,
      "away_fifa_rank": 10,
      "rank_gap": 3,
      "home_win_pct": 36.3,
      "draw_pct": 27.9,
      "away_win_pct": 35.9,
      "home_expected_goals": 1.39,
      "away_expected_goals": 1.38
    },
    {
      "home_team_id": "NED",
      "away_team_id": "MEX",
      "home_fifa_rank": 7,
      "away_fifa_rank": 14,
      "rank_gap": 7,
      "home_win_pct": 43.9,
      "draw_pct": 27.3,
      "away_win_pct": 28.8,
      "home_expected_goals": 1.56,
      "away_expected_goals": 1.23
    },
    {
      "home_team_id": "NED",
      "away_team_id": "COL",
      "home_fifa_rank": 7,
      "away_fifa_rank": 14,
      "rank_gap": 7,
      "home_win_pct": 41.0,
      "draw_pct": 27.6,
      "away_win_pct": 31.4,
      "home_expected_goals": 1.49,
      "away_expected_goals": 1.28
    },
    {
      "home_team_id": "NED",
      "away_team_id": "URU",
      "home_fifa_rank": 7,
      "away_fifa_rank": 16,
      "rank_gap": 9,
      "home_win_pct": 45.6,
      "draw_pct": 27.0,
      "away_win_pct": 27.4,
      "home_expected_goals": 1.6,
      "away_expected_goals": 1.2
    },
    {
      "home_team_id": "NED",
      "away_team_id": "USA",
      "home_fifa_rank": 7,
      "away_fifa_rank": 17,
      "rank_gap": 10,
      "home_win_pct": 41.5,
      "draw_pct": 27.6,
      "away_win_pct": 31.0,
      "home_expected_goals": 1.5,
      "away_expected_goals": 1.27
    },
    {
      "home_team_id": "NED",
      "away_team_id": "JPN",
      "home_fifa_rank": 7,
      "away_fifa_rank": 18,
      "rank_gap": 11,
      "home_win_pct": 41.2,
      "draw_pct": 27.6,
      "away_win_pct": 31.2,
      "home_expected_goals": 1.5,
      "away_expected_goals": 1.28
    },
    {
      "home_team_id": "NED",
      "away_team_id": "SEN",
      "home_fifa_rank": 7,
      "away_fifa_rank": 18,
      "rank_gap": 11,
      "home_win_pct": 45.1,
      "draw_pct": 27.1,
      "away_win_pct": 27.8,
      "home_expected_goals": 1.59,
      "away_expected_goals": 1.21
    },
    {
      "home_team_id": "NED",
      "away_team_id": "SUI",
      "home_fifa_rank": 7,
      "away_fifa_rank": 19,
      "rank_gap": 12,
      "home_win_pct": 51.3,
      "draw_pct": 25.9,
      "away_win_pct": 22.8,
      "home_expected_goals": 1.74,
      "away_expected_goals": 1.1
    },
    {
      "home_team_id": "NED",
      "away_team_id": "IRN",
      "home_fifa_rank": 7,
      "away_fifa_rank": 20,
      "rank_gap": 13,
      "home_win_pct": 56.0,
      "draw_pct": 24.6,
      "away_win_pct": 19.4,
      "home_expected_goals": 1.87,
      "away_expected_goals": 1.03
    },
    {
      "home_team_id": "NED",
      "away_team_id": "TUR",
      "home_fifa_rank": 7,
      "away_fifa_rank": 22,
      "rank_gap": 15,
      "home_win_pct": 43.3,
      "draw_pct": 27.4,
      "away_win_pct": 29.3,
      "home_expected_goals": 1.55,
      "away_expected_goals": 1.24
    },
    {
      "home_team_id": "MAR",
      "away_team_id": "BEL",
      "home_fifa_rank": 8,
      "away_fifa_rank": 9,
      "rank_gap": 1,
      "home_win_pct": 38.2,
      "draw_pct": 27.8,
      "away_win_pct": 33.9,
      "home_expected_goals": 1.43,
      "away_expected_goals": 1.34
    },
    {
      "home_team_id": "MAR",
      "away_team_id": "GER",
      "home_fifa_rank": 8,
      "away_fifa_rank": 10,
      "rank_gap": 2,
      "home_win_pct": 37.1,
      "draw_pct": 27.8,
      "away_win_pct": 35.0,
      "home_expected_goals": 1.41,
      "away_expected_goals": 1.36
    },
    {
      "home_team_id": "MAR",
      "away_team_id": "CRO",
      "home_fifa_rank": 8,
      "away_fifa_rank": 10,
      "rank_gap": 2,
      "home_win_pct": 37.6,
      "draw_pct": 27.8,
      "away_win_pct": 34.6,
      "home_expected_goals": 1.42,
      "away_expected_goals": 1.35
    },
    {
      "home_team_id": "MAR",
      "away_team_id": "MEX",
      "home_fifa_rank": 8,
      "away_fifa_rank": 14,
      "rank_gap": 6,
      "home_win_pct": 45.3,
      "draw_pct": 27.1,
      "away_win_pct": 27.6,
      "home_expected_goals": 1.59,
      "away_expected_goals": 1.2
    },
    {
      "home_team_id": "MAR",
      "away_team_id": "COL",
      "home_fifa_rank": 8,
      "away_fifa_rank": 14,
      "rank_gap": 6,
      "home_win_pct": 42.3,
      "draw_pct": 27.5,
      "away_win_pct": 30.2,
      "home_expected_goals": 1.52,
      "away_expected_goals": 1.26
    },
    {
      "home_team_id": "MAR",
      "away_team_id": "URU",
      "home_fifa_rank": 8,
      "away_fifa_rank": 16,
      "rank_gap": 8,
      "home_win_pct": 47.0,
      "draw_pct": 26.8,
      "away_win_pct": 26.2,
      "home_expected_goals": 1.63,
      "away_expected_goals": 1.17
    },
    {
      "home_team_id": "MAR",
      "away_team_id": "USA",
      "home_fifa_rank": 8,
      "away_fifa_rank": 17,
      "rank_gap": 9,
      "home_win_pct": 42.8,
      "draw_pct": 27.4,
      "away_win_pct": 29.7,
      "home_expected_goals": 1.54,
      "away_expected_goals": 1.25
    },
    {
      "home_team_id": "MAR",
      "away_team_id": "JPN",
      "home_fifa_rank": 8,
      "away_fifa_rank": 18,
      "rank_gap": 10,
      "home_win_pct": 42.6,
      "draw_pct": 27.5,
      "away_win_pct": 30.0,
      "home_expected_goals": 1.53,
      "away_expected_goals": 1.25
    },
    {
      "home_team_id": "MAR",
      "away_team_id": "SEN",
      "home_fifa_rank": 8,
      "away_fifa_rank": 18,
      "rank_gap": 10,
      "home_win_pct": 46.5,
      "draw_pct": 26.9,
      "away_win_pct": 26.6,
      "home_expected_goals": 1.62,
      "away_expected_goals": 1.18
    },
    {
      "home_team_id": "MAR",
      "away_team_id": "SUI",
      "home_fifa_rank": 8,
      "away_fifa_rank": 19,
      "rank_gap": 11,
      "home_win_pct": 52.7,
      "draw_pct": 25.5,
      "away_win_pct": 21.8,
      "home_expected_goals": 1.78,
      "away_expected_goals": 1.08
    },
    {
      "home_team_id": "MAR",
      "away_team_id": "IRN",
      "home_fifa_rank": 8,
      "away_fifa_rank": 20,
      "rank_gap": 12,
      "home_win_pct": 57.4,
      "draw_pct": 24.1,
      "away_win_pct": 18.5,
      "home_expected_goals": 1.91,
      "away_expected_goals": 1.0
    },
    {
      "home_team_id": "MAR",
      "away_team_id": "TUR",
      "home_fifa_rank": 8,
      "away_fifa_rank": 22,
      "rank_gap": 14,
      "home_win_pct": 44.7,
      "draw_pct": 27.2,
      "away_win_pct": 28.1,
      "home_expected_goals": 1.58,
      "away_expected_goals": 1.21
    },
    {
      "home_team_id": "BEL",
      "away_team_id": "GER",
      "home_fifa_rank": 9,
      "away_fifa_rank": 10,
      "rank_gap": 1,
      "home_win_pct": 36.5,
      "draw_pct": 27.9,
      "away_win_pct": 35.6,
      "home_expected_goals": 1.39,
      "away_expected_goals": 1.37
    },
    {
      "home_team_id": "BEL",
      "away_team_id": "CRO",
      "home_fifa_rank": 9,
      "away_fifa_rank": 10,
      "rank_gap": 1,
      "home_win_pct": 37.0,
      "draw_pct": 27.8,
      "away_win_pct": 35.2,
      "home_expected_goals": 1.4,
      "away_expected_goals": 1.36
    },
    {
      "home_team_id": "BEL",
      "away_team_id": "MEX",
      "home_fifa_rank": 9,
      "away_fifa_rank": 14,
      "rank_gap": 5,
      "home_win_pct": 44.7,
      "draw_pct": 27.2,
      "away_win_pct": 28.2,
      "home_expected_goals": 1.58,
      "away_expected_goals": 1.21
    },
    {
      "home_team_id": "BEL",
      "away_team_id": "COL",
      "home_fifa_rank": 9,
      "away_fifa_rank": 14,
      "rank_gap": 5,
      "home_win_pct": 41.7,
      "draw_pct": 27.6,
      "away_win_pct": 30.7,
      "home_expected_goals": 1.51,
      "away_expected_goals": 1.27
    },
    {
      "home_team_id": "BEL",
      "away_team_id": "URU",
      "home_fifa_rank": 9,
      "away_fifa_rank": 16,
      "rank_gap": 7,
      "home_win_pct": 46.4,
      "draw_pct": 26.9,
      "away_win_pct": 26.7,
      "home_expected_goals": 1.62,
      "away_expected_goals": 1.18
    },
    {
      "home_team_id": "BEL",
      "away_team_id": "USA",
      "home_fifa_rank": 9,
      "away_fifa_rank": 17,
      "rank_gap": 8,
      "home_win_pct": 42.2,
      "draw_pct": 27.5,
      "away_win_pct": 30.3,
      "home_expected_goals": 1.52,
      "away_expected_goals": 1.26
    },
    {
      "home_team_id": "BEL",
      "away_team_id": "JPN",
      "home_fifa_rank": 9,
      "away_fifa_rank": 18,
      "rank_gap": 9,
      "home_win_pct": 42.0,
      "draw_pct": 27.5,
      "away_win_pct": 30.5,
      "home_expected_goals": 1.52,
      "away_expected_goals": 1.26
    },
    {
      "home_team_id": "BEL",
      "away_team_id": "SEN",
      "home_fifa_rank": 9,
      "away_fifa_rank": 18,
      "rank_gap": 9,
      "home_win_pct": 45.9,
      "draw_pct": 27.0,
      "away_win_pct": 27.1,
      "home_expected_goals": 1.61,
      "away_expected_goals": 1.19
    },
    {
      "home_team_id": "BEL",
      "away_team_id": "SUI",
      "home_fifa_rank": 9,
      "away_fifa_rank": 19,
      "rank_gap": 10,
      "home_win_pct": 52.1,
      "draw_pct": 25.7,
      "away_win_pct": 22.3,
      "home_expected_goals": 1.76,
      "away_expected_goals": 1.09
    },
    {
      "home_team_id": "BEL",
      "away_team_id": "IRN",
      "home_fifa_rank": 9,
      "away_fifa_rank": 20,
      "rank_gap": 11,
      "home_win_pct": 56.8,
      "draw_pct": 24.3,
      "away_win_pct": 18.9,
      "home_expected_goals": 1.89,
      "away_expected_goals": 1.01
    },
    {
      "home_team_id": "BEL",
      "away_team_id": "TUR",
      "home_fifa_rank": 9,
      "away_fifa_rank": 22,
      "rank_gap": 13,
      "home_win_pct": 44.1,
      "draw_pct": 27.3,
      "away_win_pct": 28.6,
      "home_expected_goals": 1.57,
      "away_expected_goals": 1.22
    },
    {
      "home_team_id": "GER",
      "away_team_id": "CRO",
      "home_fifa_rank": 10,
      "away_fifa_rank": 10,
      "rank_gap": 0,
      "home_win_pct": 38.1,
      "draw_pct": 27.8,
      "away_win_pct": 34.1,
      "home_expected_goals": 1.43,
      "away_expected_goals": 1.34
    },
    {
      "home_team_id": "GER",
      "away_team_id": "MEX",
      "home_fifa_rank": 10,
      "away_fifa_rank": 14,
      "rank_gap": 4,
      "home_win_pct": 45.8,
      "draw_pct": 27.0,
      "away_win_pct": 27.2,
      "home_expected_goals": 1.61,
      "away_expected_goals": 1.19
    },
    {
      "home_team_id": "GER",
      "away_team_id": "COL",
      "home_fifa_rank": 10,
      "away_fifa_rank": 14,
      "rank_gap": 4,
      "home_win_pct": 42.9,
      "draw_pct": 27.4,
      "away_win_pct": 29.7,
      "home_expected_goals": 1.54,
      "away_expected_goals": 1.25
    },
    {
      "home_team_id": "GER",
      "away_team_id": "URU",
      "home_fifa_rank": 10,
      "away_fifa_rank": 16,
      "rank_gap": 6,
      "home_win_pct": 47.6,
      "draw_pct": 26.7,
      "away_win_pct": 25.7,
      "home_expected_goals": 1.65,
      "away_expected_goals": 1.16
    },
    {
      "home_team_id": "GER",
      "away_team_id": "USA",
      "home_fifa_rank": 10,
      "away_fifa_rank": 17,
      "rank_gap": 7,
      "home_win_pct": 43.4,
      "draw_pct": 27.4,
      "away_win_pct": 29.3,
      "home_expected_goals": 1.55,
      "away_expected_goals": 1.24
    },
    {
      "home_team_id": "GER",
      "away_team_id": "JPN",
      "home_fifa_rank": 10,
      "away_fifa_rank": 18,
      "rank_gap": 8,
      "home_win_pct": 43.1,
      "draw_pct": 27.4,
      "away_win_pct": 29.5,
      "home_expected_goals": 1.54,
      "away_expected_goals": 1.24
    },
    {
      "home_team_id": "GER",
      "away_team_id": "SEN",
      "home_fifa_rank": 10,
      "away_fifa_rank": 18,
      "rank_gap": 8,
      "home_win_pct": 47.1,
      "draw_pct": 26.8,
      "away_win_pct": 26.2,
      "home_expected_goals": 1.64,
      "away_expected_goals": 1.17
    },
    {
      "home_team_id": "GER",
      "away_team_id": "SUI",
      "home_fifa_rank": 10,
      "away_fifa_rank": 19,
      "rank_gap": 9,
      "home_win_pct": 53.2,
      "draw_pct": 25.4,
      "away_win_pct": 21.4,
      "home_expected_goals": 1.79,
      "away_expected_goals": 1.07
    },
    {
      "home_team_id": "GER",
      "away_team_id": "IRN",
      "home_fifa_rank": 10,
      "away_fifa_rank": 20,
      "rank_gap": 10,
      "home_win_pct": 57.9,
      "draw_pct": 24.0,
      "away_win_pct": 18.1,
      "home_expected_goals": 1.92,
      "away_expected_goals": 1.0
    },
    {
      "home_team_id": "GER",
      "away_team_id": "TUR",
      "home_fifa_rank": 10,
      "away_fifa_rank": 22,
      "rank_gap": 12,
      "home_win_pct": 45.3,
      "draw_pct": 27.1,
      "away_win_pct": 27.6,
      "home_expected_goals": 1.59,
      "away_expected_goals": 1.2
    },
    {
      "home_team_id": "CRO",
      "away_team_id": "MEX",
      "home_fifa_rank": 10,
      "away_fifa_rank": 14,
      "rank_gap": 4,
      "home_win_pct": 45.4,
      "draw_pct": 27.1,
      "away_win_pct": 27.6,
      "home_expected_goals": 1.6,
      "away_expected_goals": 1.2
    },
    {
      "home_team_id": "CRO",
      "away_team_id": "COL",
      "home_fifa_rank": 10,
      "away_fifa_rank": 14,
      "rank_gap": 4,
      "home_win_pct": 42.4,
      "draw_pct": 27.5,
      "away_win_pct": 30.1,
      "home_expected_goals": 1.53,
      "away_expected_goals": 1.25
    },
    {
      "home_team_id": "CRO",
      "away_team_id": "URU",
      "home_fifa_rank": 10,
      "away_fifa_rank": 16,
      "rank_gap": 6,
      "home_win_pct": 47.1,
      "draw_pct": 26.8,
      "away_win_pct": 26.1,
      "home_expected_goals": 1.64,
      "away_expected_goals": 1.17
    },
    {
      "home_team_id": "CRO",
      "away_team_id": "USA",
      "home_fifa_rank": 10,
      "away_fifa_rank": 17,
      "rank_gap": 7,
      "home_win_pct": 42.9,
      "draw_pct": 27.4,
      "away_win_pct": 29.7,
      "home_expected_goals": 1.54,
      "away_expected_goals": 1.25
    },
    {
      "home_team_id": "CRO",
      "away_team_id": "JPN",
      "home_fifa_rank": 10,
      "away_fifa_rank": 18,
      "rank_gap": 8,
      "home_win_pct": 42.7,
      "draw_pct": 27.5,
      "away_win_pct": 29.9,
      "home_expected_goals": 1.53,
      "away_expected_goals": 1.25
    },
    {
      "home_team_id": "CRO",
      "away_team_id": "SEN",
      "home_fifa_rank": 10,
      "away_fifa_rank": 18,
      "rank_gap": 8,
      "home_win_pct": 46.6,
      "draw_pct": 26.9,
      "away_win_pct": 26.5,
      "home_expected_goals": 1.63,
      "away_expected_goals": 1.18
    },
    {
      "home_team_id": "CRO",
      "away_team_id": "SUI",
      "home_fifa_rank": 10,
      "away_fifa_rank": 19,
      "rank_gap": 9,
      "home_win_pct": 52.8,
      "draw_pct": 25.5,
      "away_win_pct": 21.7,
      "home_expected_goals": 1.78,
      "away_expected_goals": 1.08
    },
    {
      "home_team_id": "CRO",
      "away_team_id": "IRN",
      "home_fifa_rank": 10,
      "away_fifa_rank": 20,
      "rank_gap": 10,
      "home_win_pct": 57.5,
      "draw_pct": 24.1,
      "away_win_pct": 18.4,
      "home_expected_goals": 1.91,
      "away_expected_goals": 1.0
    },
    {
      "home_team_id": "CRO",
      "away_team_id": "TUR",
      "home_fifa_rank": 10,
      "away_fifa_rank": 22,
      "rank_gap": 12,
      "home_win_pct": 44.8,
      "draw_pct": 27.2,
      "away_win_pct": 28.0,
      "home_expected_goals": 1.58,
      "away_expected_goals": 1.21
    },
    {
      "home_team_id": "MEX",
      "away_team_id": "COL",
      "home_fifa_rank": 14,
      "away_fifa_rank": 14,
      "rank_gap": 0,
      "home_win_pct": 34.9,
      "draw_pct": 27.8,
      "away_win_pct": 37.3,
      "home_expected_goals": 1.36,
      "away_expected_goals": 1.41
    },
    {
      "home_team_id": "MEX",
      "away_team_id": "URU",
      "home_fifa_rank": 14,
      "away_fifa_rank": 16,
      "rank_gap": 2,
      "home_win_pct": 39.3,
      "draw_pct": 27.8,
      "away_win_pct": 32.9,
      "home_expected_goals": 1.46,
      "away_expected_goals": 1.32
    },
    {
      "home_team_id": "MEX",
      "away_team_id": "USA",
      "home_fifa_rank": 14,
      "away_fifa_rank": 17,
      "rank_gap": 3,
      "home_win_pct": 35.3,
      "draw_pct": 27.8,
      "away_win_pct": 36.8,
      "home_expected_goals": 1.37,
      "away_expected_goals": 1.4
    },
    {
      "home_team_id": "MEX",
      "away_team_id": "JPN",
      "home_fifa_rank": 14,
      "away_fifa_rank": 18,
      "rank_gap": 4,
      "home_win_pct": 35.1,
      "draw_pct": 27.8,
      "away_win_pct": 37.1,
      "home_expected_goals": 1.36,
      "away_expected_goals": 1.41
    },
    {
      "home_team_id": "MEX",
      "away_team_id": "SEN",
      "home_fifa_rank": 14,
      "away_fifa_rank": 18,
      "rank_gap": 4,
      "home_win_pct": 38.8,
      "draw_pct": 27.8,
      "away_win_pct": 33.4,
      "home_expected_goals": 1.45,
      "away_expected_goals": 1.33
    },
    {
      "home_team_id": "MEX",
      "away_team_id": "SUI",
      "home_fifa_rank": 14,
      "away_fifa_rank": 19,
      "rank_gap": 5,
      "home_win_pct": 44.9,
      "draw_pct": 27.2,
      "away_win_pct": 28.0,
      "home_expected_goals": 1.58,
      "away_expected_goals": 1.21
    },
    {
      "home_team_id": "MEX",
      "away_team_id": "IRN",
      "home_fifa_rank": 14,
      "away_fifa_rank": 20,
      "rank_gap": 6,
      "home_win_pct": 49.6,
      "draw_pct": 26.3,
      "away_win_pct": 24.2,
      "home_expected_goals": 1.7,
      "away_expected_goals": 1.13
    },
    {
      "home_team_id": "MEX",
      "away_team_id": "TUR",
      "home_fifa_rank": 14,
      "away_fifa_rank": 22,
      "rank_gap": 8,
      "home_win_pct": 37.1,
      "draw_pct": 27.8,
      "away_win_pct": 35.0,
      "home_expected_goals": 1.41,
      "away_expected_goals": 1.36
    },
    {
      "home_team_id": "COL",
      "away_team_id": "URU",
      "home_fifa_rank": 14,
      "away_fifa_rank": 16,
      "rank_gap": 2,
      "home_win_pct": 42.2,
      "draw_pct": 27.5,
      "away_win_pct": 30.3,
      "home_expected_goals": 1.52,
      "away_expected_goals": 1.26
    },
    {
      "home_team_id": "COL",
      "away_team_id": "USA",
      "home_fifa_rank": 14,
      "away_fifa_rank": 17,
      "rank_gap": 3,
      "home_win_pct": 38.1,
      "draw_pct": 27.8,
      "away_win_pct": 34.1,
      "home_expected_goals": 1.43,
      "away_expected_goals": 1.34
    },
    {
      "home_team_id": "COL",
      "away_team_id": "JPN",
      "home_fifa_rank": 14,
      "away_fifa_rank": 18,
      "rank_gap": 4,
      "home_win_pct": 37.9,
      "draw_pct": 27.8,
      "away_win_pct": 34.3,
      "home_expected_goals": 1.42,
      "away_expected_goals": 1.35
    },
    {
      "home_team_id": "COL",
      "away_team_id": "SEN",
      "home_fifa_rank": 14,
      "away_fifa_rank": 18,
      "rank_gap": 4,
      "home_win_pct": 41.7,
      "draw_pct": 27.6,
      "away_win_pct": 30.7,
      "home_expected_goals": 1.51,
      "away_expected_goals": 1.27
    },
    {
      "home_team_id": "COL",
      "away_team_id": "SUI",
      "home_fifa_rank": 14,
      "away_fifa_rank": 19,
      "rank_gap": 5,
      "home_win_pct": 47.8,
      "draw_pct": 26.6,
      "away_win_pct": 25.5,
      "home_expected_goals": 1.65,
      "away_expected_goals": 1.16
    },
    {
      "home_team_id": "COL",
      "away_team_id": "IRN",
      "home_fifa_rank": 14,
      "away_fifa_rank": 20,
      "rank_gap": 6,
      "home_win_pct": 52.5,
      "draw_pct": 25.6,
      "away_win_pct": 21.9,
      "home_expected_goals": 1.77,
      "away_expected_goals": 1.08
    },
    {
      "home_team_id": "COL",
      "away_team_id": "TUR",
      "home_fifa_rank": 14,
      "away_fifa_rank": 22,
      "rank_gap": 8,
      "home_win_pct": 40.0,
      "draw_pct": 27.7,
      "away_win_pct": 32.3,
      "home_expected_goals": 1.47,
      "away_expected_goals": 1.3
    },
    {
      "home_team_id": "URU",
      "away_team_id": "USA",
      "home_fifa_rank": 16,
      "away_fifa_rank": 17,
      "rank_gap": 1,
      "home_win_pct": 33.7,
      "draw_pct": 27.8,
      "away_win_pct": 38.5,
      "home_expected_goals": 1.33,
      "away_expected_goals": 1.44
    },
    {
      "home_team_id": "URU",
      "away_team_id": "JPN",
      "home_fifa_rank": 16,
      "away_fifa_rank": 18,
      "rank_gap": 2,
      "home_win_pct": 33.5,
      "draw_pct": 27.8,
      "away_win_pct": 38.7,
      "home_expected_goals": 1.33,
      "away_expected_goals": 1.44
    },
    {
      "home_team_id": "URU",
      "away_team_id": "SEN",
      "home_fifa_rank": 16,
      "away_fifa_rank": 18,
      "rank_gap": 2,
      "home_win_pct": 37.2,
      "draw_pct": 27.8,
      "away_win_pct": 35.0,
      "home_expected_goals": 1.41,
      "away_expected_goals": 1.36
    },
    {
      "home_team_id": "URU",
      "away_team_id": "SUI",
      "home_fifa_rank": 16,
      "away_fifa_rank": 19,
      "rank_gap": 3,
      "home_win_pct": 43.1,
      "draw_pct": 27.4,
      "away_win_pct": 29.5,
      "home_expected_goals": 1.54,
      "away_expected_goals": 1.24
    },
    {
      "home_team_id": "URU",
      "away_team_id": "IRN",
      "home_fifa_rank": 16,
      "away_fifa_rank": 20,
      "rank_gap": 4,
      "home_win_pct": 47.8,
      "draw_pct": 26.6,
      "away_win_pct": 25.5,
      "home_expected_goals": 1.66,
      "away_expected_goals": 1.16
    },
    {
      "home_team_id": "URU",
      "away_team_id": "TUR",
      "home_fifa_rank": 16,
      "away_fifa_rank": 22,
      "rank_gap": 6,
      "home_win_pct": 35.5,
      "draw_pct": 27.8,
      "away_win_pct": 36.6,
      "home_expected_goals": 1.37,
      "away_expected_goals": 1.4
    },
    {
      "home_team_id": "USA",
      "away_team_id": "JPN",
      "home_fifa_rank": 17,
      "away_fifa_rank": 18,
      "rank_gap": 1,
      "home_win_pct": 37.4,
      "draw_pct": 27.8,
      "away_win_pct": 34.8,
      "home_expected_goals": 1.41,
      "away_expected_goals": 1.36
    },
    {
      "home_team_id": "USA",
      "away_team_id": "SEN",
      "home_fifa_rank": 17,
      "away_fifa_rank": 18,
      "rank_gap": 1,
      "home_win_pct": 41.2,
      "draw_pct": 27.6,
      "away_win_pct": 31.2,
      "home_expected_goals": 1.5,
      "away_expected_goals": 1.28
    },
    {
      "home_team_id": "USA",
      "away_team_id": "SUI",
      "home_fifa_rank": 17,
      "away_fifa_rank": 19,
      "rank_gap": 2,
      "home_win_pct": 47.3,
      "draw_pct": 26.7,
      "away_win_pct": 25.9,
      "home_expected_goals": 1.64,
      "away_expected_goals": 1.17
    },
    {
      "home_team_id": "USA",
      "away_team_id": "IRN",
      "home_fifa_rank": 17,
      "away_fifa_rank": 20,
      "rank_gap": 3,
      "home_win_pct": 52.0,
      "draw_pct": 25.7,
      "away_win_pct": 22.3,
      "home_expected_goals": 1.76,
      "away_expected_goals": 1.09
    },
    {
      "home_team_id": "USA",
      "away_team_id": "TUR",
      "home_fifa_rank": 17,
      "away_fifa_rank": 22,
      "rank_gap": 5,
      "home_win_pct": 39.5,
      "draw_pct": 27.7,
      "away_win_pct": 32.8,
      "home_expected_goals": 1.46,
      "away_expected_goals": 1.31
    },
    {
      "home_team_id": "JPN",
      "away_team_id": "SEN",
      "home_fifa_rank": 18,
      "away_fifa_rank": 18,
      "rank_gap": 0,
      "home_win_pct": 41.5,
      "draw_pct": 27.6,
      "away_win_pct": 30.9,
      "home_expected_goals": 1.51,
      "away_expected_goals": 1.27
    },
    {
      "home_team_id": "JPN",
      "away_team_id": "SUI",
      "home_fifa_rank": 18,
      "away_fifa_rank": 19,
      "rank_gap": 1,
      "home_win_pct": 47.6,
      "draw_pct": 26.7,
      "away_win_pct": 25.7,
      "home_expected_goals": 1.65,
      "away_expected_goals": 1.16
    },
    {
      "home_team_id": "JPN",
      "away_team_id": "IRN",
      "home_fifa_rank": 18,
      "away_fifa_rank": 20,
      "rank_gap": 2,
      "home_win_pct": 52.3,
      "draw_pct": 25.6,
      "away_win_pct": 22.1,
      "home_expected_goals": 1.77,
      "away_expected_goals": 1.08
    },
    {
      "home_team_id": "JPN",
      "away_team_id": "TUR",
      "home_fifa_rank": 18,
      "away_fifa_rank": 22,
      "rank_gap": 4,
      "home_win_pct": 39.8,
      "draw_pct": 27.7,
      "away_win_pct": 32.5,
      "home_expected_goals": 1.47,
      "away_expected_goals": 1.31
    },
    {
      "home_team_id": "SEN",
      "away_team_id": "SUI",
      "home_fifa_rank": 18,
      "away_fifa_rank": 19,
      "rank_gap": 1,
      "home_win_pct": 43.6,
      "draw_pct": 27.3,
      "away_win_pct": 29.0,
      "home_expected_goals": 1.56,
      "away_expected_goals": 1.23
    },
    {
      "home_team_id": "SEN",
      "away_team_id": "IRN",
      "home_fifa_rank": 18,
      "away_fifa_rank": 20,
      "rank_gap": 2,
      "home_win_pct": 48.3,
      "draw_pct": 26.5,
      "away_win_pct": 25.1,
      "home_expected_goals": 1.67,
      "away_expected_goals": 1.15
    },
    {
      "home_team_id": "SEN",
      "away_team_id": "TUR",
      "home_fifa_rank": 18,
      "away_fifa_rank": 22,
      "rank_gap": 4,
      "home_win_pct": 36.0,
      "draw_pct": 27.9,
      "away_win_pct": 36.2,
      "home_expected_goals": 1.38,
      "away_expected_goals": 1.39
    },
    {
      "home_team_id": "SUI",
      "away_team_id": "IRN",
      "home_fifa_rank": 19,
      "away_fifa_rank": 20,
      "rank_gap": 1,
      "home_win_pct": 42.2,
      "draw_pct": 27.5,
      "away_win_pct": 30.3,
      "home_expected_goals": 1.52,
      "away_expected_goals": 1.26
    },
    {
      "home_team_id": "SUI",
      "away_team_id": "TUR",
      "home_fifa_rank": 19,
      "away_fifa_rank": 22,
      "rank_gap": 3,
      "home_win_pct": 30.4,
      "draw_pct": 27.5,
      "away_win_pct": 42.1,
      "home_expected_goals": 1.26,
      "away_expected_goals": 1.52
    },
    {
      "home_team_id": "IRN",
      "away_team_id": "TUR",
      "home_fifa_rank": 20,
      "away_fifa_rank": 22,
      "rank_gap": 2,
      "home_win_pct": 26.4,
      "draw_pct": 26.8,
      "away_win_pct": 46.7,
      "home_expected_goals": 1.18,
      "away_expected_goals": 1.63
    }
  ],
  "implausibleMatchupWarnings": [
    {
      "home_team_id": "ESP",
      "away_team_id": "JPN",
      "home_fifa_rank": 2,
      "away_fifa_rank": 18,
      "rank_gap": 16,
      "home_win_pct": 50.9,
      "draw_pct": 26.0,
      "away_win_pct": 23.1,
      "home_expected_goals": 1.73,
      "away_expected_goals": 1.11,
      "warning": "ESP (FIFA #2) is given only 50.9% to beat JPN (FIFA #18), a 16-rank gap."
    },
    {
      "home_team_id": "ESP",
      "away_team_id": "TUR",
      "home_fifa_rank": 2,
      "away_fifa_rank": 22,
      "rank_gap": 20,
      "home_win_pct": 53.1,
      "draw_pct": 25.4,
      "away_win_pct": 21.5,
      "home_expected_goals": 1.79,
      "away_expected_goals": 1.07,
      "warning": "ESP (FIFA #2) is given only 53.1% to beat TUR (FIFA #22), a 20-rank gap."
    },
    {
      "home_team_id": "FRA",
      "away_team_id": "TUR",
      "home_fifa_rank": 3,
      "away_fifa_rank": 22,
      "rank_gap": 19,
      "home_win_pct": 53.2,
      "draw_pct": 25.4,
      "away_win_pct": 21.4,
      "home_expected_goals": 1.79,
      "away_expected_goals": 1.07,
      "warning": "FRA (FIFA #3) is given only 53.2% to beat TUR (FIFA #22), a 19-rank gap."
    },
    {
      "home_team_id": "ENG",
      "away_team_id": "TUR",
      "home_fifa_rank": 4,
      "away_fifa_rank": 22,
      "rank_gap": 18,
      "home_win_pct": 52.9,
      "draw_pct": 25.5,
      "away_win_pct": 21.6,
      "home_expected_goals": 1.78,
      "away_expected_goals": 1.07,
      "warning": "ENG (FIFA #4) is given only 52.9% to beat TUR (FIFA #22), a 18-rank gap."
    },
    {
      "home_team_id": "POR",
      "away_team_id": "JPN",
      "home_fifa_rank": 5,
      "away_fifa_rank": 18,
      "rank_gap": 13,
      "home_win_pct": 47.3,
      "draw_pct": 26.7,
      "away_win_pct": 25.9,
      "home_expected_goals": 1.64,
      "away_expected_goals": 1.17,
      "warning": "POR (FIFA #5) is given only 47.3% to beat JPN (FIFA #18), a 13-rank gap."
    },
    {
      "home_team_id": "POR",
      "away_team_id": "TUR",
      "home_fifa_rank": 5,
      "away_fifa_rank": 22,
      "rank_gap": 17,
      "home_win_pct": 49.5,
      "draw_pct": 26.3,
      "away_win_pct": 24.2,
      "home_expected_goals": 1.7,
      "away_expected_goals": 1.13,
      "warning": "POR (FIFA #5) is given only 49.5% to beat TUR (FIFA #22), a 17-rank gap."
    },
    {
      "home_team_id": "BRA",
      "away_team_id": "USA",
      "home_fifa_rank": 6,
      "away_fifa_rank": 17,
      "rank_gap": 11,
      "home_win_pct": 43.9,
      "draw_pct": 27.3,
      "away_win_pct": 28.8,
      "home_expected_goals": 1.56,
      "away_expected_goals": 1.23,
      "warning": "BRA (FIFA #6) is given only 43.9% to beat USA (FIFA #17), a 11-rank gap."
    },
    {
      "home_team_id": "BRA",
      "away_team_id": "JPN",
      "home_fifa_rank": 6,
      "away_fifa_rank": 18,
      "rank_gap": 12,
      "home_win_pct": 43.6,
      "draw_pct": 27.3,
      "away_win_pct": 29.0,
      "home_expected_goals": 1.55,
      "away_expected_goals": 1.23,
      "warning": "BRA (FIFA #6) is given only 43.6% to beat JPN (FIFA #18), a 12-rank gap."
    },
    {
      "home_team_id": "BRA",
      "away_team_id": "TUR",
      "home_fifa_rank": 6,
      "away_fifa_rank": 22,
      "rank_gap": 16,
      "home_win_pct": 45.8,
      "draw_pct": 27.0,
      "away_win_pct": 27.2,
      "home_expected_goals": 1.61,
      "away_expected_goals": 1.19,
      "warning": "BRA (FIFA #6) is given only 45.8% to beat TUR (FIFA #22), a 16-rank gap."
    },
    {
      "home_team_id": "NED",
      "away_team_id": "GER",
      "home_fifa_rank": 7,
      "away_fifa_rank": 10,
      "rank_gap": 3,
      "home_win_pct": 35.8,
      "draw_pct": 27.9,
      "away_win_pct": 36.3,
      "home_expected_goals": 1.38,
      "away_expected_goals": 1.39,
      "warning": "NED (FIFA #7) is given only 35.8% to beat GER (FIFA #10), a 3-rank gap."
    },
    {
      "home_team_id": "NED",
      "away_team_id": "CRO",
      "home_fifa_rank": 7,
      "away_fifa_rank": 10,
      "rank_gap": 3,
      "home_win_pct": 36.3,
      "draw_pct": 27.9,
      "away_win_pct": 35.9,
      "home_expected_goals": 1.39,
      "away_expected_goals": 1.38,
      "warning": "NED (FIFA #7) is given only 36.3% to beat CRO (FIFA #10), a 3-rank gap."
    },
    {
      "home_team_id": "NED",
      "away_team_id": "COL",
      "home_fifa_rank": 7,
      "away_fifa_rank": 14,
      "rank_gap": 7,
      "home_win_pct": 41.0,
      "draw_pct": 27.6,
      "away_win_pct": 31.4,
      "home_expected_goals": 1.49,
      "away_expected_goals": 1.28,
      "warning": "NED (FIFA #7) is given only 41.0% to beat COL (FIFA #14), a 7-rank gap."
    },
    {
      "home_team_id": "NED",
      "away_team_id": "USA",
      "home_fifa_rank": 7,
      "away_fifa_rank": 17,
      "rank_gap": 10,
      "home_win_pct": 41.5,
      "draw_pct": 27.6,
      "away_win_pct": 31.0,
      "home_expected_goals": 1.5,
      "away_expected_goals": 1.27,
      "warning": "NED (FIFA #7) is given only 41.5% to beat USA (FIFA #17), a 10-rank gap."
    },
    {
      "home_team_id": "NED",
      "away_team_id": "JPN",
      "home_fifa_rank": 7,
      "away_fifa_rank": 18,
      "rank_gap": 11,
      "home_win_pct": 41.2,
      "draw_pct": 27.6,
      "away_win_pct": 31.2,
      "home_expected_goals": 1.5,
      "away_expected_goals": 1.28,
      "warning": "NED (FIFA #7) is given only 41.2% to beat JPN (FIFA #18), a 11-rank gap."
    },
    {
      "home_team_id": "NED",
      "away_team_id": "SEN",
      "home_fifa_rank": 7,
      "away_fifa_rank": 18,
      "rank_gap": 11,
      "home_win_pct": 45.1,
      "draw_pct": 27.1,
      "away_win_pct": 27.8,
      "home_expected_goals": 1.59,
      "away_expected_goals": 1.21,
      "warning": "NED (FIFA #7) is given only 45.1% to beat SEN (FIFA #18), a 11-rank gap."
    },
    {
      "home_team_id": "NED",
      "away_team_id": "TUR",
      "home_fifa_rank": 7,
      "away_fifa_rank": 22,
      "rank_gap": 15,
      "home_win_pct": 43.3,
      "draw_pct": 27.4,
      "away_win_pct": 29.3,
      "home_expected_goals": 1.55,
      "away_expected_goals": 1.24,
      "warning": "NED (FIFA #7) is given only 43.3% to beat TUR (FIFA #22), a 15-rank gap."
    },
    {
      "home_team_id": "MAR",
      "away_team_id": "USA",
      "home_fifa_rank": 8,
      "away_fifa_rank": 17,
      "rank_gap": 9,
      "home_win_pct": 42.8,
      "draw_pct": 27.4,
      "away_win_pct": 29.7,
      "home_expected_goals": 1.54,
      "away_expected_goals": 1.25,
      "warning": "MAR (FIFA #8) is given only 42.8% to beat USA (FIFA #17), a 9-rank gap."
    },
    {
      "home_team_id": "MAR",
      "away_team_id": "JPN",
      "home_fifa_rank": 8,
      "away_fifa_rank": 18,
      "rank_gap": 10,
      "home_win_pct": 42.6,
      "draw_pct": 27.5,
      "away_win_pct": 30.0,
      "home_expected_goals": 1.53,
      "away_expected_goals": 1.25,
      "warning": "MAR (FIFA #8) is given only 42.6% to beat JPN (FIFA #18), a 10-rank gap."
    },
    {
      "home_team_id": "MAR",
      "away_team_id": "TUR",
      "home_fifa_rank": 8,
      "away_fifa_rank": 22,
      "rank_gap": 14,
      "home_win_pct": 44.7,
      "draw_pct": 27.2,
      "away_win_pct": 28.1,
      "home_expected_goals": 1.58,
      "away_expected_goals": 1.21,
      "warning": "MAR (FIFA #8) is given only 44.7% to beat TUR (FIFA #22), a 14-rank gap."
    },
    {
      "home_team_id": "BEL",
      "away_team_id": "USA",
      "home_fifa_rank": 9,
      "away_fifa_rank": 17,
      "rank_gap": 8,
      "home_win_pct": 42.2,
      "draw_pct": 27.5,
      "away_win_pct": 30.3,
      "home_expected_goals": 1.52,
      "away_expected_goals": 1.26,
      "warning": "BEL (FIFA #9) is given only 42.2% to beat USA (FIFA #17), a 8-rank gap."
    },
    {
      "home_team_id": "BEL",
      "away_team_id": "JPN",
      "home_fifa_rank": 9,
      "away_fifa_rank": 18,
      "rank_gap": 9,
      "home_win_pct": 42.0,
      "draw_pct": 27.5,
      "away_win_pct": 30.5,
      "home_expected_goals": 1.52,
      "away_expected_goals": 1.26,
      "warning": "BEL (FIFA #9) is given only 42.0% to beat JPN (FIFA #18), a 9-rank gap."
    },
    {
      "home_team_id": "BEL",
      "away_team_id": "TUR",
      "home_fifa_rank": 9,
      "away_fifa_rank": 22,
      "rank_gap": 13,
      "home_win_pct": 44.1,
      "draw_pct": 27.3,
      "away_win_pct": 28.6,
      "home_expected_goals": 1.57,
      "away_expected_goals": 1.22,
      "warning": "BEL (FIFA #9) is given only 44.1% to beat TUR (FIFA #22), a 13-rank gap."
    },
    {
      "home_team_id": "GER",
      "away_team_id": "TUR",
      "home_fifa_rank": 10,
      "away_fifa_rank": 22,
      "rank_gap": 12,
      "home_win_pct": 45.3,
      "draw_pct": 27.1,
      "away_win_pct": 27.6,
      "home_expected_goals": 1.59,
      "away_expected_goals": 1.2,
      "warning": "GER (FIFA #10) is given only 45.3% to beat TUR (FIFA #22), a 12-rank gap."
    },
    {
      "home_team_id": "CRO",
      "away_team_id": "TUR",
      "home_fifa_rank": 10,
      "away_fifa_rank": 22,
      "rank_gap": 12,
      "home_win_pct": 44.8,
      "draw_pct": 27.2,
      "away_win_pct": 28.0,
      "home_expected_goals": 1.58,
      "away_expected_goals": 1.21,
      "warning": "CRO (FIFA #10) is given only 44.8% to beat TUR (FIFA #22), a 12-rank gap."
    },
    {
      "home_team_id": "MEX",
      "away_team_id": "USA",
      "home_fifa_rank": 14,
      "away_fifa_rank": 17,
      "rank_gap": 3,
      "home_win_pct": 35.3,
      "draw_pct": 27.8,
      "away_win_pct": 36.8,
      "home_expected_goals": 1.37,
      "away_expected_goals": 1.4,
      "warning": "MEX (FIFA #14) is given only 35.3% to beat USA (FIFA #17), a 3-rank gap."
    },
    {
      "home_team_id": "MEX",
      "away_team_id": "JPN",
      "home_fifa_rank": 14,
      "away_fifa_rank": 18,
      "rank_gap": 4,
      "home_win_pct": 35.1,
      "draw_pct": 27.8,
      "away_win_pct": 37.1,
      "home_expected_goals": 1.36,
      "away_expected_goals": 1.41,
      "warning": "MEX (FIFA #14) is given only 35.1% to beat JPN (FIFA #18), a 4-rank gap."
    },
    {
      "home_team_id": "MEX",
      "away_team_id": "TUR",
      "home_fifa_rank": 14,
      "away_fifa_rank": 22,
      "rank_gap": 8,
      "home_win_pct": 37.1,
      "draw_pct": 27.8,
      "away_win_pct": 35.0,
      "home_expected_goals": 1.41,
      "away_expected_goals": 1.36,
      "warning": "MEX (FIFA #14) is given only 37.1% to beat TUR (FIFA #22), a 8-rank gap."
    },
    {
      "home_team_id": "COL",
      "away_team_id": "TUR",
      "home_fifa_rank": 14,
      "away_fifa_rank": 22,
      "rank_gap": 8,
      "home_win_pct": 40.0,
      "draw_pct": 27.7,
      "away_win_pct": 32.3,
      "home_expected_goals": 1.47,
      "away_expected_goals": 1.3,
      "warning": "COL (FIFA #14) is given only 40.0% to beat TUR (FIFA #22), a 8-rank gap."
    },
    {
      "home_team_id": "URU",
      "away_team_id": "USA",
      "home_fifa_rank": 16,
      "away_fifa_rank": 17,
      "rank_gap": 1,
      "home_win_pct": 33.7,
      "draw_pct": 27.8,
      "away_win_pct": 38.5,
      "home_expected_goals": 1.33,
      "away_expected_goals": 1.44,
      "warning": "URU (FIFA #16) is given only 33.7% to beat USA (FIFA #17), a 1-rank gap."
    },
    {
      "home_team_id": "URU",
      "away_team_id": "JPN",
      "home_fifa_rank": 16,
      "away_fifa_rank": 18,
      "rank_gap": 2,
      "home_win_pct": 33.5,
      "draw_pct": 27.8,
      "away_win_pct": 38.7,
      "home_expected_goals": 1.33,
      "away_expected_goals": 1.44,
      "warning": "URU (FIFA #16) is given only 33.5% to beat JPN (FIFA #18), a 2-rank gap."
    },
    {
      "home_team_id": "URU",
      "away_team_id": "TUR",
      "home_fifa_rank": 16,
      "away_fifa_rank": 22,
      "rank_gap": 6,
      "home_win_pct": 35.5,
      "draw_pct": 27.8,
      "away_win_pct": 36.6,
      "home_expected_goals": 1.37,
      "away_expected_goals": 1.4,
      "warning": "URU (FIFA #16) is given only 35.5% to beat TUR (FIFA #22), a 6-rank gap."
    },
    {
      "home_team_id": "SEN",
      "away_team_id": "TUR",
      "home_fifa_rank": 18,
      "away_fifa_rank": 22,
      "rank_gap": 4,
      "home_win_pct": 36.0,
      "draw_pct": 27.9,
      "away_win_pct": 36.2,
      "home_expected_goals": 1.38,
      "away_expected_goals": 1.39,
      "warning": "SEN (FIFA #18) is given only 36.0% to beat TUR (FIFA #22), a 4-rank gap."
    },
    {
      "home_team_id": "SUI",
      "away_team_id": "TUR",
      "home_fifa_rank": 19,
      "away_fifa_rank": 22,
      "rank_gap": 3,
      "home_win_pct": 30.4,
      "draw_pct": 27.5,
      "away_win_pct": 42.1,
      "home_expected_goals": 1.26,
      "away_expected_goals": 1.52,
      "warning": "SUI (FIFA #19) is given only 30.4% to beat TUR (FIFA #22), a 3-rank gap."
    },
    {
      "home_team_id": "IRN",
      "away_team_id": "TUR",
      "home_fifa_rank": 20,
      "away_fifa_rank": 22,
      "rank_gap": 2,
      "home_win_pct": 26.4,
      "draw_pct": 26.8,
      "away_win_pct": 46.7,
      "home_expected_goals": 1.18,
      "away_expected_goals": 1.63,
      "warning": "IRN (FIFA #20) is given only 26.4% to beat TUR (FIFA #22), a 2-rank gap."
    }
  ],
  "frequentRankUnderperformers": [
    {
      "team_id": "NED",
      "implausible_matchup_count": 7
    },
    {
      "team_id": "BRA",
      "implausible_matchup_count": 3
    },
    {
      "team_id": "MAR",
      "implausible_matchup_count": 3
    },
    {
      "team_id": "BEL",
      "implausible_matchup_count": 3
    },
    {
      "team_id": "MEX",
      "implausible_matchup_count": 3
    },
    {
      "team_id": "URU",
      "implausible_matchup_count": 3
    }
  ],
  "hostAdvantageCheck": [
    {
      "host_team_id": "CAN",
      "reference_opponent_id": "SWE",
      "home_win_pct_with_host_bump": 37.9,
      "home_win_pct_without_host_bump": 31.6,
      "delta_pp": 6.3
    },
    {
      "host_team_id": "MEX",
      "reference_opponent_id": "SWE",
      "home_win_pct_with_host_bump": 44.2,
      "home_win_pct_without_host_bump": 37.2,
      "delta_pp": 7.0
    },
    {
      "host_team_id": "USA",
      "reference_opponent_id": "SWE",
      "home_win_pct_with_host_bump": 46.7,
      "home_win_pct_without_host_bump": 39.6,
      "delta_pp": 7.1
    }
  ],
  "tacticalModifierCheck": {
    "high_press_team_id": "CAN",
    "press_intensity": 88,
    "high_possession_team_id": "ESP",
    "possession_style": 88,
    "tactical_modifier_for_high_press_team_at_home": 0.05,
    "note": "Positive value nudges expected goals toward the home (high-press) team, per poisson_model.py's documented formula."
  },
  "underdogWinRateCheck": {
    "underdog_definition": "bottom half of teams by FIFA rank",
    "underdog_team_count": 24,
    "by_sample_size": {
      "100": {
        "underdog_champion_pct_sum": 9.0,
        "underdog_round_of_16_pct_sum": 447.0
      },
      "500": {
        "underdog_champion_pct_sum": 9.4,
        "underdog_round_of_16_pct_sum": 448.8
      }
    },
    "champion_pct_at_500_iterations": {
      "BRA": 4.0,
      "ARG": 22.6,
      "FRA": 8.6,
      "ENG": 9.8,
      "GER": 6.6,
      "USA": 4.6,
      "MEX": 3.8,
      "CAN": 2.8,
      "SUI": 0.2,
      "MAR": 1.8,
      "PAR": 0.2,
      "AUS": 0.2,
      "ECU": 0.2,
      "NED": 4.6,
      "JPN": 2.4,
      "SWE": 1.0,
      "BEL": 2.2,
      "EGY": 1.6,
      "ESP": 9.4,
      "SEN": 0.2,
      "NOR": 2.4,
      "ALG": 2.0,
      "AUT": 0.2,
      "POR": 3.6,
      "COD": 0.2,
      "COL": 1.8,
      "CRO": 3.0
    }
  },
  "championOddsConcentration": {
    "uniform_pct_if_equal_chance": 2.08,
    "top1_champion_pct": 22.6,
    "top3_champion_pct_sum": 41.8,
    "top5_champion_pct_sum": 57.0,
    "teams_with_nonzero_champion_pct": 27,
    "assessment": "reasonable"
  },
  "warnings": [
    "ESP (FIFA #2) is given only 50.9% to beat JPN (FIFA #18), a 16-rank gap.",
    "ESP (FIFA #2) is given only 53.1% to beat TUR (FIFA #22), a 20-rank gap.",
    "FRA (FIFA #3) is given only 53.2% to beat TUR (FIFA #22), a 19-rank gap.",
    "ENG (FIFA #4) is given only 52.9% to beat TUR (FIFA #22), a 18-rank gap.",
    "POR (FIFA #5) is given only 47.3% to beat JPN (FIFA #18), a 13-rank gap.",
    "POR (FIFA #5) is given only 49.5% to beat TUR (FIFA #22), a 17-rank gap.",
    "BRA (FIFA #6) is given only 43.9% to beat USA (FIFA #17), a 11-rank gap.",
    "BRA (FIFA #6) is given only 43.6% to beat JPN (FIFA #18), a 12-rank gap.",
    "BRA (FIFA #6) is given only 45.8% to beat TUR (FIFA #22), a 16-rank gap.",
    "NED (FIFA #7) is given only 35.8% to beat GER (FIFA #10), a 3-rank gap.",
    "NED (FIFA #7) is given only 36.3% to beat CRO (FIFA #10), a 3-rank gap.",
    "NED (FIFA #7) is given only 41.0% to beat COL (FIFA #14), a 7-rank gap.",
    "NED (FIFA #7) is given only 41.5% to beat USA (FIFA #17), a 10-rank gap.",
    "NED (FIFA #7) is given only 41.2% to beat JPN (FIFA #18), a 11-rank gap.",
    "NED (FIFA #7) is given only 45.1% to beat SEN (FIFA #18), a 11-rank gap.",
    "NED (FIFA #7) is given only 43.3% to beat TUR (FIFA #22), a 15-rank gap.",
    "MAR (FIFA #8) is given only 42.8% to beat USA (FIFA #17), a 9-rank gap.",
    "MAR (FIFA #8) is given only 42.6% to beat JPN (FIFA #18), a 10-rank gap.",
    "MAR (FIFA #8) is given only 44.7% to beat TUR (FIFA #22), a 14-rank gap.",
    "BEL (FIFA #9) is given only 42.2% to beat USA (FIFA #17), a 8-rank gap.",
    "BEL (FIFA #9) is given only 42.0% to beat JPN (FIFA #18), a 9-rank gap.",
    "BEL (FIFA #9) is given only 44.1% to beat TUR (FIFA #22), a 13-rank gap.",
    "GER (FIFA #10) is given only 45.3% to beat TUR (FIFA #22), a 12-rank gap.",
    "CRO (FIFA #10) is given only 44.8% to beat TUR (FIFA #22), a 12-rank gap.",
    "MEX (FIFA #14) is given only 35.3% to beat USA (FIFA #17), a 3-rank gap.",
    "MEX (FIFA #14) is given only 35.1% to beat JPN (FIFA #18), a 4-rank gap.",
    "MEX (FIFA #14) is given only 37.1% to beat TUR (FIFA #22), a 8-rank gap.",
    "COL (FIFA #14) is given only 40.0% to beat TUR (FIFA #22), a 8-rank gap.",
    "URU (FIFA #16) is given only 33.7% to beat USA (FIFA #17), a 1-rank gap.",
    "URU (FIFA #16) is given only 33.5% to beat JPN (FIFA #18), a 2-rank gap.",
    "URU (FIFA #16) is given only 35.5% to beat TUR (FIFA #22), a 6-rank gap.",
    "SEN (FIFA #18) is given only 36.0% to beat TUR (FIFA #22), a 4-rank gap.",
    "SUI (FIFA #19) is given only 30.4% to beat TUR (FIFA #22), a 3-rank gap.",
    "IRN (FIFA #20) is given only 26.4% to beat TUR (FIFA #22), a 2-rank gap.",
    "NED is the better-FIFA-ranked side in 7 matchups where the model still doesn't clearly favor it -- its squad-derived rating may undershoot its FIFA rank.",
    "BRA is the better-FIFA-ranked side in 3 matchups where the model still doesn't clearly favor it -- its squad-derived rating may undershoot its FIFA rank.",
    "MAR is the better-FIFA-ranked side in 3 matchups where the model still doesn't clearly favor it -- its squad-derived rating may undershoot its FIFA rank.",
    "BEL is the better-FIFA-ranked side in 3 matchups where the model still doesn't clearly favor it -- its squad-derived rating may undershoot its FIFA rank.",
    "MEX is the better-FIFA-ranked side in 3 matchups where the model still doesn't clearly favor it -- its squad-derived rating may undershoot its FIFA rank.",
    "URU is the better-FIFA-ranked side in 3 matchups where the model still doesn't clearly favor it -- its squad-derived rating may undershoot its FIFA rank."
  ],
  "recommendedChanges": [
    "Squad-rating review (not a formula change): NED (7 matchups), BRA (3 matchups), MAR (3 matchups), BEL (3 matchups), MEX (3 matchups), URU (3 matchups) consistently underperform their FIFA rank in this model. Worth a Codex review of these teams' player attributes/qualitative_adjustments rather than a global ModelConfig change."
  ]
}